etb/__init__.py
etb/__init__.pyi
etb/_etb.cpython-310-x86_64-linux-gnu.so
etb/_version.py
etb/py.typed
explodethosebits.libs/libcudart-c3a75b33.so.12.8.90
include/etb/bit_coordinate.hpp
include/etb/bit_extraction.hpp
include/etb/bit_pruning.hpp
include/etb/config.hpp
include/etb/early_stopping.hpp
include/etb/etb.hpp
include/etb/heuristics.hpp
include/etb/memoization.hpp
include/etb/path.hpp
include/etb/path_count.hpp
include/etb/path_generator.hpp
include/etb/prefix_trie.hpp
include/etb/reporting.hpp
include/etb/scoring.hpp
include/etb/signature.hpp
include/etb/cuda/arch_optimizations.cuh
include/etb/cuda/blackwell_optimizations.cuh
include/etb/cuda/cuda_common.cuh
include/etb/cuda/etb_cuda.cuh
include/etb/cuda/gpu_memory.cuh
include/etb/cuda/heuristics_kernel.cuh
include/etb/cuda/path_generator_kernel.cuh
include/etb/cuda/prefix_pruner_kernel.cuh
include/etb/cuda/signature_kernel.cuh
include/gmock/gmock-actions.h
include/gmock/gmock-cardinalities.h
include/gmock/gmock-function-mocker.h
include/gmock/gmock-matchers.h
include/gmock/gmock-more-actions.h
include/gmock/gmock-more-matchers.h
include/gmock/gmock-nice-strict.h
include/gmock/gmock-spec-builders.h
include/gmock/gmock.h
include/gmock/internal/gmock-internal-utils.h
include/gmock/internal/gmock-port.h
include/gmock/internal/gmock-pp.h
include/gmock/internal/custom/README.md
include/gmock/internal/custom/gmock-generated-actions.h
include/gmock/internal/custom/gmock-matchers.h
include/gmock/internal/custom/gmock-port.h
include/gtest/gtest-assertion-result.h
include/gtest/gtest-death-test.h
include/gtest/gtest-matchers.h
include/gtest/gtest-message.h
include/gtest/gtest-param-test.h
include/gtest/gtest-printers.h
include/gtest/gtest-spi.h
include/gtest/gtest-test-part.h
include/gtest/gtest-typed-test.h
include/gtest/gtest.h
include/gtest/gtest_pred_impl.h
include/gtest/gtest_prod.h
include/gtest/internal/gtest-death-test-internal.h
explodethosebits-0.3.0.dist-info/METADATA
explodethosebits-0.3.0.dist-info/WHEEL
explodethosebits-0.3.0.dist-info/RECORD
explodethosebits-0.3.0.dist-info/licenses/LICENSE
explodethosebits-0.3.0.dist-info/sboms/auditwheel.cdx.json
