Metadata-Version: 2.2
Name: explodethosebits
Version: 0.3.0
Summary: ExplodeThoseBits - CUDA-accelerated exhaustive bit tree analysis
Keywords: forensics,bit-extraction,cuda,data-recovery,file-signatures,heuristics
Author-Email: Odin Glynn-Martin <odin@odinglynn.com>
License: MIT
Classifier: Development Status :: 3 - Alpha
Classifier: Intended Audience :: Developers
Classifier: Intended Audience :: Science/Research
Classifier: License :: OSI Approved :: MIT License
Classifier: Operating System :: OS Independent
Classifier: Programming Language :: Python :: 3
Classifier: Programming Language :: Python :: 3.8
Classifier: Programming Language :: Python :: 3.9
Classifier: Programming Language :: Python :: 3.10
Classifier: Programming Language :: Python :: 3.11
Classifier: Programming Language :: Python :: 3.12
Classifier: Programming Language :: C++
Classifier: Topic :: Scientific/Engineering
Classifier: Topic :: Security
Classifier: Topic :: System :: Recovery Tools
Project-URL: Homepage, https://github.com/odinglyn0/etb
Project-URL: Repository, https://github.com/odinglyn0/etb
Project-URL: Issues, https://github.com/odinglyn0/etb/issues
Requires-Python: >=3.8
Provides-Extra: test
Requires-Dist: pytest>=7.0.0; extra == "test"
Requires-Dist: pytest-cov>=4.0.0; extra == "test"
Requires-Dist: hypothesis>=6.0.0; extra == "test"
Provides-Extra: dev
Requires-Dist: pytest>=7.0.0; extra == "dev"
Requires-Dist: pytest-cov>=4.0.0; extra == "dev"
Requires-Dist: hypothesis>=6.0.0; extra == "dev"
Requires-Dist: black>=23.0.0; extra == "dev"
Requires-Dist: isort>=5.0.0; extra == "dev"
Requires-Dist: mypy>=1.0.0; extra == "dev"
